terry/__init__.py
terry/api.py
terry/controller.py
terry/worker.py
terry-0.1.0.dist-info/METADATA
terry-0.1.0.dist-info/RECORD
terry-0.1.0.dist-info/WHEEL
terry-0.1.0.dist-info/top_level.txt
