Metadata-Version: 2.1
Name: terry
Version: 0.1.0
Summary: Distributed task queue
Home-page: https://github.com/werat/terry
Author: Andy Yankovsky
Author-email: weratt@gmail.com
License: MIT
Platform: UNKNOWN
Classifier: Programming Language :: Python
Classifier: Programming Language :: Python :: 2.7
Classifier: Programming Language :: Python :: 3.5
Classifier: Programming Language :: Python :: 3.6
Classifier: Programming Language :: Python :: Implementation :: CPython
Requires-Dist: pymongo (<=3.4.0)
